{
  "slug": "rd",
  "name": "Recurring Deposit (RD) Calculator",
  "description": "Compute returns on recurring deposits.",
  "category": "Savings",
  "tags": ["rd", "recurring-deposit", "savings", "bank", "interest", "finance", "investment", "calculator"],
  "fields": [
    {
      "key": "monthly",
      "label": "Monthly Deposit (₹)",
      "type": "number",
      "placeholder": "5000"
    },
    {
      "key": "rate",
      "label": "Annual Interest (%)",
      "type": "percentage",
      "placeholder": "7"
    },
    {
      "key": "years",
      "label": "Years",
      "type": "number",
      "placeholder": "5"
    },
    {
      "key": "frequency",
      "label": "Compounding Frequency (per year)",
      "type": "number",
      "placeholder": "12"
    }
  ],
  "formula": "Maturity = P * ((1+r/n)^(n*t) - 1) / (1 - (1+r/n)^(-1/n))",
  "computationType": "rd",
  "outputs": [
    {
      "key": "maturityAmount",
      "label": "Maturity Amount (₹)",
      "format": "currency"
    },
    {
      "key": "totalDeposited",
      "label": "Total Deposited (₹)",
      "format": "currency"
    },
    {
      "key": "interestEarned",
      "label": "Interest Earned (₹)",
      "format": "currency"
    }
  ],
  "example": {
    "inputs": {
      "monthly": 5000,
      "rate": 7,
      "years": 5,
      "frequency": 12
    },
    "outputs": {
      "maturityAmount": 331564.23,
      "totalDeposited": 300000,
      "interestEarned": 31564.23
    },
    "explanation": "Recurring deposits accumulate monthly investments with compound interest."
  },
  "faqs": [
    {
      "question": "Is the interest compounded?",
      "answer": "Yes, RD interest is typically compounded quarterly or monthly depending on the bank."
    },
    {
      "question": "What happens if I miss a deposit?",
      "answer": "Skipping deposits can reduce the maturity value since contributions are lower."
    },
    {
      "question": "Can I break my RD?",
      "answer": "Yes, you can break an RD before maturity, usually with a small penalty on interest."
    }
  ]
}
